{
  "parent": "minecraft:recipes/root",
  "rewards": {
    "recipes": [
      "minecraft:brown_crystal_from_smelting_waxed_brown_corundum"
    ]
  },
  "criteria": {
    "has_waxed_brown_corundum": {
      "trigger": "minecraft:inventory_changed",
      "conditions": {
        "items": [
          {
            "items": [
              "terrains:waxed_brown_corundum"
            ]
          }
        ]
      }
    },
    "has_the_recipe": {
      "trigger": "minecraft:recipe_unlocked",
      "conditions": {
        "recipe": "minecraft:brown_crystal_from_smelting_waxed_brown_corundum"
      }
    }
  },
  "requirements": [
    [
      "has_waxed_brown_corundum",
      "has_the_recipe"
    ]
  ]
}